.gitignore
MANIFEST.in
README.rst
bootstrap.py
buildout.cfg
setup.py
kombinat/__init__.py
kombinat.decogrid.egg-info/PKG-INFO
kombinat.decogrid.egg-info/SOURCES.txt
kombinat.decogrid.egg-info/dependency_links.txt
kombinat.decogrid.egg-info/entry_points.txt
kombinat.decogrid.egg-info/namespace_packages.txt
kombinat.decogrid.egg-info/not-zip-safe
kombinat.decogrid.egg-info/requires.txt
kombinat.decogrid.egg-info/top_level.txt
kombinat/decogrid/__init__.py
kombinat/decogrid/deco.css
kombinat/decogrid/grid-test.pt
kombinat/decogrid/grid.py