Metadata-Version: 1.1
Name: kombinat.decogrid
Version: 0.3
Summary: A decogrid generator for plone columns.css file.
Home-page: http://svn.plone.org/svn/collective/kombinat.decogrid/trunk
Author: Daniel Widerin
Author-email: daniel.widerin@kombinat.at
License: GPL
Keywords: decogrid
Platform: UNKNOWN
Classifier: Framework :: Plone
Classifier: Environment :: Console
Classifier: Programming Language :: Python
